{
  "$schema": "../schemas/signing.schema.json",
  "namespace": "infinitas-skill",
  "allowed_signers": "config/allowed_signers",
  "signature_ext": ".ssig",
  "git_tag": {
    "format": "ssh",
    "allowed_signers": "config/allowed_signers",
    "remote": "origin",
    "signing_key_env": "INFINITAS_SKILL_GIT_SIGNING_KEY",
    "note": "Stable releases require repo-managed verified SSH-signed git tags"
  },
  "attestation": {
    "format": "ssh",
    "namespace": "infinitas-skill",
    "allowed_signers": "config/allowed_signers",
    "signature_ext": ".ssig",
    "signing_key_env": "INFINITAS_SKILL_GIT_SIGNING_KEY",
    "ci": {
      "provider": "github-actions",
      "repository": "lvxiaoer/infinitas-skill",
      "workflow": "release-attestation"
    },
    "policy": {
      "mode": "enforce",
      "release_trust_mode": "ssh",
      "require_verified_attestation_for_release_output": true,
      "require_verified_attestation_for_distribution": true
    },
    "note": "Stable release provenance must be SSH-signed and verified against repo-managed allowed signers"
  },
  "note": "SSH signing settings for stable release tags and release attestations"
}
